py_datastructures/Stack.py
py_datastructures/__init__.py
py_datastructures/test_Stack.py
py_datastructures-0.1.2.dist-info/DESCRIPTION.rst
py_datastructures-0.1.2.dist-info/METADATA
py_datastructures-0.1.2.dist-info/RECORD
py_datastructures-0.1.2.dist-info/WHEEL
py_datastructures-0.1.2.dist-info/metadata.json
py_datastructures-0.1.2.dist-info/top_level.txt
