Metadata-Version: 2.0
Name: py-datastructures
Version: 0.1.2
Summary: Data Structures using Python
Home-page: https://github.com/AdithyaYelloju/Data-Structures-in-Python
Author: Adithya Yelloju
Author-email: adithyayelloju@gmail.com
License: UNKNOWN
Platform: UNKNOWN
